ZetcodeJavaJiaochengChuyiFix1/README.md
ZetcodeJavaJiaochengChuyiFix1/__init__.py
ZetcodeJavaJiaochengChuyiFix1/__main__.py
ZetcodeJavaJiaochengChuyiFix1/file.epub
ZetcodeJavaJiaochengChuyiFix1/index.html
ZetcodeJavaJiaochengChuyiFix1/css/__init__.py
ZetcodeJavaJiaochengChuyiFix1/css/annotations.css
ZetcodeJavaJiaochengChuyiFix1/css/main.css
ZetcodeJavaJiaochengChuyiFix1/css/normalize.css
ZetcodeJavaJiaochengChuyiFix1/css/popup.css
ZetcodeJavaJiaochengChuyiFix1/font/__init__.py
ZetcodeJavaJiaochengChuyiFix1/font/fontello.eot
ZetcodeJavaJiaochengChuyiFix1/font/fontello.svg
ZetcodeJavaJiaochengChuyiFix1/font/fontello.ttf
ZetcodeJavaJiaochengChuyiFix1/font/fontello.woff
ZetcodeJavaJiaochengChuyiFix1/img/__init__.py
ZetcodeJavaJiaochengChuyiFix1/img/annotator-glyph-sprite.png
ZetcodeJavaJiaochengChuyiFix1/img/annotator-icon-sprite.png
ZetcodeJavaJiaochengChuyiFix1/img/apple-touch-icon.png
ZetcodeJavaJiaochengChuyiFix1/img/cancelfullscreen.png
ZetcodeJavaJiaochengChuyiFix1/img/close.png
ZetcodeJavaJiaochengChuyiFix1/img/fullscreen.png
ZetcodeJavaJiaochengChuyiFix1/img/loader.gif
ZetcodeJavaJiaochengChuyiFix1/img/menu-icon.png
ZetcodeJavaJiaochengChuyiFix1/img/save.png
ZetcodeJavaJiaochengChuyiFix1/img/saved.png
ZetcodeJavaJiaochengChuyiFix1/img/settings-s.png
ZetcodeJavaJiaochengChuyiFix1/img/settings.png
ZetcodeJavaJiaochengChuyiFix1/img/star.png
ZetcodeJavaJiaochengChuyiFix1/js/__init__.py
ZetcodeJavaJiaochengChuyiFix1/js/epub.js
ZetcodeJavaJiaochengChuyiFix1/js/epub.min.js
ZetcodeJavaJiaochengChuyiFix1/js/epub.min.map
ZetcodeJavaJiaochengChuyiFix1/js/hooks.min.js
ZetcodeJavaJiaochengChuyiFix1/js/hooks.min.map
ZetcodeJavaJiaochengChuyiFix1/js/reader.js
ZetcodeJavaJiaochengChuyiFix1/js/reader.js.map
ZetcodeJavaJiaochengChuyiFix1/js/reader.min.js
ZetcodeJavaJiaochengChuyiFix1/js/reader.min.map
ZetcodeJavaJiaochengChuyiFix1/js/hooks/__init__.py
ZetcodeJavaJiaochengChuyiFix1/js/hooks/extensions/__init__.py
ZetcodeJavaJiaochengChuyiFix1/js/hooks/extensions/highlight.js
zetcode_java_jiaocheng_chuyi_fix1-2025.3.24.0.dist-info/METADATA
zetcode_java_jiaocheng_chuyi_fix1-2025.3.24.0.dist-info/WHEEL
zetcode_java_jiaocheng_chuyi_fix1-2025.3.24.0.dist-info/entry_points.txt
zetcode_java_jiaocheng_chuyi_fix1-2025.3.24.0.dist-info/top_level.txt
zetcode_java_jiaocheng_chuyi_fix1-2025.3.24.0.dist-info/RECORD
